Workbook

Sheet Instrucciones
A1: Registro de la ronda completa de pruebas (08/10, tras unir las ramas en main)
A3: Cómo usarlo
A4: 1. Antes de empezar, haz los pasos 1 a 3 de docs\GUIA_PRUEBAS_EXCEL.md (pasar a main, arranque limpio, preparar aurora-base.xlsx y cronograma-base.xlsx).
A5: 2. Ve a la hoja «Pruebas». Sigue las filas en orden (columna Orden). La columna «Libro» dice qué archivo abrir; «Pasos» y «Esperado» están copiados de la guía.
A6: 3. En «Resultado» elige OK, Falla, No aplica o Pendiente. Si es Falla, escribe en «Qué ves» lo que sale y guarda una captura con el código en el nombre (por ejemplo GT21.png).
A7: 4. La hoja «Resumen» cuenta los resultados por bloque. Filtra la hoja Pruebas por Bloque o por Resultado con las flechas del encabezado.
A8: 5. Al final de cada día, guarda y mándame este archivo con las capturas.
A10: Los libros
A11: aurora-base.xlsx: copia de ejemplos\demo-proyecto-aurora.xlsx con «Rellenar las hojas de prueba» (Diagnóstico). No se toca: para cada bloque, una copia (aurora-A.xlsx, aurora-D.xlsx…).
A12: cronograma-base.xlsx: libro en blanco → Cronograma → Crear libro de cronograma (Obra) con Config!B2 = 04/01/2027, Config!B9 = 31/01/2028 y Hitos_Contrato!B2 = 31/01/2028. No se toca: una copia por bloque (cronograma-Q.xlsx, cronograma-GT1.xlsx…).
A13: Para copiar, en PowerShell: Copy-Item "$HOME\Desktop\aurora-base.xlsx" "$HOME\Desktop\aurora-A.xlsx"
A14: tests\fixtures\qrsa\: R1-simple.xml, R2-relaciones.xml, R3-calendario.xml, R1-simple.xer (importar y ProjectLibre).
... A17: Este archivo se genera desde la guía con: python3 docs/pruebas/generar-registro.py

Sheet Pruebas
A1: Orden | B1: Bloque | C1: Código | D1: Prueba | E1: Libro | F1: Pasos | G1: Esperado | H1: Resultado | I1: Qué ves / notas | J1: Captura | K1: Fecha
A2: 1 | B2: 01. Preparación (P0) | C2: P0 | D2: En la cinta, la pestaña Riesgo tiene cuatro botones: | E2: Cualquier libro | F2: En la cinta, la pestaña Riesgo tiene cuatro botones: Modelo, Resultados, Configuración y Diagnóstico. Al pulsar Modelo se abre el panel (no se queda en blanco). | G2: (Lo esperado está en los pasos.) | H2: Pendiente
A3: 2 | B3: 02. A · Lo básico (hoja «Modelo») | C3: A1 | D3: Valores base | E3: aurora-A.xlsx (copia de aurora-base.xlsx) | F3: Sin tocar nada: - Modelo!C32 = 366.372 € - C33 = 22,1 % - C34 = 942.185 € | G3: (Lo esperado está en los pasos.) | H3: Pendiente
A4: 3 | B4: 02. A · Lo básico (hoja «Modelo») | C4: A2 | D4: Marcar con nombres legibles | E4: aurora-A.xlsx (copia de aurora-base.xlsx) | F4: Botón Modelo. Selecciona C5 y pulsa «Añadir la selección como entrada». - Esperado: - La entrada se llama «Precio unitario» (el texto de su izquierda), no «Modelo!C5». - La celda se pinta de amarillo. - El panel le propone una triangular de 108 a 132. | G4: (Lo esperado está en los pasos.) | H4: Pendiente
A5: 4 | B5: 02. A · Lo básico (hoja «Modelo») | C5: A3 | D5: Vista previa | E5: aurora-A.xlsx (copia de aurora-base.xlsx) | F5: Abre la entrada C5 y cámbiala a Triangular 105 / 120 / 140 (la distribución de la hoja «Instrucciones»). - Esperado: debajo de los campos, un dibujo de la distribución que cambia según escribes, con «p5 … · p50 … · p95 … · media …». - Escribe un mínimo mayor que la moda (p. ej. 130): sale un aviso y la vista previa no se rompe. Vuelve a 105. | G5: (Lo esperado está en los pasos.) | H5: Pendiente
A6: 5 | B6: 02. A · Lo básico (hoja «Modelo») | C6: A4 | D6: Acotar | E6: aurora-A.xlsx (copia de aurora-base.xlsx) | F6: En la misma entrada, en «Acotar: mínimo» escribe 110. - Esperado: la vista previa se corta en 110 y el p5 sube. - Borra el 110: vuelve a como estaba. | G6: (Lo esperado está en los pasos.) | H6: Pendiente
A7: 6 | B7: 02. A · Lo básico (hoja «Modelo») | C7: A5 | D7: El resto del modelo | E7: aurora-A.xlsx (copia de aurora-base.xlsx) | F7: Marca también como entradas C6, C7, C8 y C9, con las distribuciones de la hoja «Instrucciones». Marca como salidas C32, C33 y C34. - Esperado: - Cada una lleva el nombre de su fila: «Unidades vendidas el año 1», «VAN al 11 %», «TIR del proyecto»… - Las salidas se pintan de verde. | G7: (Lo esperado está en los pasos.) | H7: Pendiente
A8: 7 | B8: 02. A · Lo básico (hoja «Modelo») | C8: A6 | D8: Simular | E8: aurora-A.xlsx (copia de aurora-base.xlsx) | F8: Pulsa Simular (10.000 iteraciones, motor automático). - Esperado: en «Cómo se calculó», Rápido (en memoria); tarda menos de 2 segundos. - VAN: mediana en torno a +255.000 €. | G8: (Lo esperado está en los pasos.) | H8: Pendiente
A9: 8 | B9: 02. A · Lo básico (hoja «Modelo») | C9: A7 | D9: Resumen y selector de salidas | E9: aurora-A.xlsx (copia de aurora-base.xlsx) | F9: Al principio de Resultados, una tabla «Salidas» con las tres y un desplegable «Ver». - Debajo se ve una sola salida. - Pulsa otra fila de la tabla: cambia la que se ve. - Selecciona en la hoja la celda C33: el panel salta a la TIR. | G9: (Lo esperado está en los pasos.) | H9: Pendiente
A10: 9 | B10: 02. A · Lo básico (hoja «Modelo») | C10: A8 | D10: Lectura en palabras | E10: aurora-A.xlsx (copia de aurora-base.xlsx) | F10: Debajo del nombre del VAN, un párrafo, por ejemplo: «VAN al 11 % tiene una media de…; en el 90 % de los casos simulados queda entre… y…», y qué entradas lo mueven más. | G10: (Lo esperado está en los pasos.) | H10: Pendiente
A11: 10 | B11: 02. A · Lo básico (hoja «Modelo») | C11: A9 | D11: Umbral | E11: aurora-A.xlsx (copia de aurora-base.xlsx) | F11: En el VAN: «Probabilidad de quedar por debajo de» 0, y pulsa Intro. - Esperado: - En torno a 30 %. - En el histograma, las barras a la izquierda del 0 en verde y las demás en gris. - El párrafo de A8 añade la frase de la probabilidad. | G11: (Lo esperado está en los pasos.) | H11: Pendiente
A12: 11 | B12: 02. A · Lo básico (hoja «Modelo») | C12: A10 | D12: Tornado («Qué la mueve más») | E12: aurora-A.xlsx (copia de aurora-base.xlsx) | F12: - Arriba, precio (C5) y coste variable (C8). - A la derecha de cada barra, un %. - Debajo, «Entre todas explican el X % de la variación». | G12: (Lo esperado está en los pasos.) | H12: Pendiente
A13: 12 | B13: 02. A · Lo básico (hoja «Modelo») | C13: A11 | D13: Araña («Qué pasa si cada entrada se mueve») | E13: aurora-A.xlsx (copia de aurora-base.xlsx) | F13: Una línea por entrada: - La del precio sube y la del coste variable baja. - Al pasar el ratón se lee un valor. | G13: (Lo esperado está en los pasos.) | H13: Pendiente
... A219: 218 | B219: 20. Q1–Q4 · ProjectLibre (opcional, sin Excel) | C219: Q4 | D219: Mandarme el resultado | E219: tests\fixtures\qrsa\*.xml en ProjectLibre | F219: Lo más cómodo, cualquiera de los dos: - una captura de la tabla de cada cronograma con Inicio, Fin y Holgura total; o - Archivo → Guardar como → formato XML de MS Project (R1-projectlibre.xml, etc.), y me adjuntas los tres archivos. Dime también la versión de ProjectLibre (Ayuda → Acerca de). Si algo no coincide, no lo corrijas a mano: mándamelo tal cual, y vemos si es un error mío o una convención del programa. | G219: (Lo esperado está en los pasos.) | H219: Pendiente

Sheet Resumen
A1: Bloque | B1: Pruebas | C1: OK | D1: Falla | E1: No aplica | F1: Pendiente | G1: % hecho
A2: 01. Preparación (P0) | B2: =COUNTIF(Pruebas!$B$2:$B$219,A2) | C2: =COUNTIFS(Pruebas!$B$2:$B$219,A2,Pruebas!$H$2:$H$219,"OK") | D2: =COUNTIFS(Pruebas!$B$2:$B$219,A2,Pruebas!$H$2:$H$219,"Falla") | E2: =COUNTIFS(Pruebas!$B$2:$B$219,A2,Pruebas!$H$2:$H$219,"No aplica") | F2: =COUNTIFS(Pruebas!$B$2:$B$219,A2,Pruebas!$H$2:$H$219,"Pendiente") | G2: =IF(B2=0,"",1-F2/B2)
A3: 02. A · Lo básico (hoja «Modelo») | B3: =COUNTIF(Pruebas!$B$2:$B$219,A3) | C3: =COUNTIFS(Pruebas!$B$2:$B$219,A3,Pruebas!$H$2:$H$219,"OK") | D3: =COUNTIFS(Pruebas!$B$2:$B$219,A3,Pruebas!$H$2:$H$219,"Falla") | E3: =COUNTIFS(Pruebas!$B$2:$B$219,A3,Pruebas!$H$2:$H$219,"No aplica") | F3: =COUNTIFS(Pruebas!$B$2:$B$219,A3,Pruebas!$H$2:$H$219,"Pendiente") | G3: =IF(B3=0,"",1-F3/B3)
A4: 03. B · Configuración | B4: =COUNTIF(Pruebas!$B$2:$B$219,A4) | C4: =COUNTIFS(Pruebas!$B$2:$B$219,A4,Pruebas!$H$2:$H$219,"OK") | D4: =COUNTIFS(Pruebas!$B$2:$B$219,A4,Pruebas!$H$2:$H$219,"Falla") | E4: =COUNTIFS(Pruebas!$B$2:$B$219,A4,Pruebas!$H$2:$H$219,"No aplica") | F4: =COUNTIFS(Pruebas!$B$2:$B$219,A4,Pruebas!$H$2:$H$219,"Pendiente") | G4: =IF(B4=0,"",1-F4/B4)
A5: 04. C · Proyecto, informe PDF y hoja volcada | B5: =COUNTIF(Pruebas!$B$2:$B$219,A5) | C5: =COUNTIFS(Pruebas!$B$2:$B$219,A5,Pruebas!$H$2:$H$219,"OK") | D5: =COUNTIFS(Pruebas!$B$2:$B$219,A5,Pruebas!$H$2:$H$219,"Falla") | E5: =COUNTIFS(Pruebas!$B$2:$B$219,A5,Pruebas!$H$2:$H$219,"No aplica") | F5: =COUNTIFS(Pruebas!$B$2:$B$219,A5,Pruebas!$H$2:$H$219,"Pendiente") | G5: =IF(B5=0,"",1-F5/B5)
A6: 05. D · Escenarios | B6: =COUNTIF(Pruebas!$B$2:$B$219,A6) | C6: =COUNTIFS(Pruebas!$B$2:$B$219,A6,Pruebas!$H$2:$H$219,"OK") | D6: =COUNTIFS(Pruebas!$B$2:$B$219,A6,Pruebas!$H$2:$H$219,"Falla") | E6: =COUNTIFS(Pruebas!$B$2:$B$219,A6,Pruebas!$H$2:$H$219,"No aplica") | F6: =COUNTIFS(Pruebas!$B$2:$B$219,A6,Pruebas!$H$2:$H$219,"Pendiente") | G6: =IF(B6=0,"",1-F6/B6)
A7: 05. E · Ajustar a datos | B7: =COUNTIF(Pruebas!$B$2:$B$219,A7) | C7: =COUNTIFS(Pruebas!$B$2:$B$219,A7,Pruebas!$H$2:$H$219,"OK") | D7: =COUNTIFS(Pruebas!$B$2:$B$219,A7,Pruebas!$H$2:$H$219,"Falla") | E7: =COUNTIFS(Pruebas!$B$2:$B$219,A7,Pruebas!$H$2:$H$219,"No aplica") | F7: =COUNTIFS(Pruebas!$B$2:$B$219,A7,Pruebas!$H$2:$H$219,"Pendiente") | G7: =IF(B7=0,"",1-F7/B7)
A8: 06. K · Mismos números al repetir | B8: =COUNTIF(Pruebas!$B$2:$B$219,A8) | C8: =COUNTIFS(Pruebas!$B$2:$B$219,A8,Pruebas!$H$2:$H$219,"OK") | D8: =COUNTIFS(Pruebas!$B$2:$B$219,A8,Pruebas!$H$2:$H$219,"Falla") | E8: =COUNTIFS(Pruebas!$B$2:$B$219,A8,Pruebas!$H$2:$H$219,"No aplica") | F8: =COUNTIFS(Pruebas!$B$2:$B$219,A8,Pruebas!$H$2:$H$219,"Pendiente") | G8: =IF(B8=0,"",1-F8/B8)
A9: 07. N · Etapa 2 (runtime, cinta, explorador, funciones) | B9: =COUNTIF(Pruebas!$B$2:$B$219,A9) | C9: =COUNTIFS(Pruebas!$B$2:$B$219,A9,Pruebas!$H$2:$H$219,"OK") | D9: =COUNTIFS(Pruebas!$B$2:$B$219,A9,Pruebas!$H$2:$H$219,"Falla") | E9: =COUNTIFS(Pruebas!$B$2:$B$219,A9,Pruebas!$H$2:$H$219,"No aplica") | F9: =COUNTIFS(Pruebas!$B$2:$B$219,A9,Pruebas!$H$2:$H$219,"Pendiente") | G9: =IF(B9=0,"",1-F9/B9)
A10: 08. V3 y V4 · Comparar y asistente | B10: =COUNTIF(Pruebas!$B$2:$B$219,A10) | C10: =COUNTIFS(Pruebas!$B$2:$B$219,A10,Pruebas!$H$2:$H$219,"OK") | D10: =COUNTIFS(Pruebas!$B$2:$B$219,A10,Pruebas!$H$2:$H$219,"Falla") | E10: =COUNTIFS(Pruebas!$B$2:$B$219,A10,Pruebas!$H$2:$H$219,"No aplica") | F10: =COUNTIFS(Pruebas!$B$2:$B$219,A10,Pruebas!$H$2:$H$219,"Pendiente") | G10: =IF(B10=0,"",1-F10/B10)
A11: 09. R1–R4 · Correlaciones, P80, percentiles, compatible | B11: =COUNTIF(Pruebas!$B$2:$B$219,A11) | C11: =COUNTIFS(Pruebas!$B$2:$B$219,A11,Pruebas!$H$2:$H$219,"OK") | D11: =COUNTIFS(Pruebas!$B$2:$B$219,A11,Pruebas!$H$2:$H$219,"Falla") | E11: =COUNTIFS(Pruebas!$B$2:$B$219,A11,Pruebas!$H$2:$H$219,"No aplica") | F11: =COUNTIFS(Pruebas!$B$2:$B$219,A11,Pruebas!$H$2:$H$219,"Pendiente") | G11: =IF(B11=0,"",1-F11/B11)
A12: 10. F · Funciones RIESGO (hoja «Pruebas») | B12: =COUNTIF(Pruebas!$B$2:$B$219,A12) | C12: =COUNTIFS(Pruebas!$B$2:$B$219,A12,Pruebas!$H$2:$H$219,"OK") | D12: =COUNTIFS(Pruebas!$B$2:$B$219,A12,Pruebas!$H$2:$H$219,"Falla") | E12: =COUNTIFS(Pruebas!$B$2:$B$219,A12,Pruebas!$H$2:$H$219,"No aplica") | F12: =COUNTIFS(Pruebas!$B$2:$B$219,A12,Pruebas!$H$2:$H$219,"Pendiente") | G12: =IF(B12=0,"",1-F12/B12)
A13: 10. G · LET, matrices y derrame | B13: =COUNTIF(Pruebas!$B$2:$B$219,A13) | C13: =COUNTIFS(Pruebas!$B$2:$B$219,A13,Pruebas!$H$2:$H$219,"OK") | D13: =COUNTIFS(Pruebas!$B$2:$B$219,A13,Pruebas!$H$2:$H$219,"Falla") | E13: =COUNTIFS(Pruebas!$B$2:$B$219,A13,Pruebas!$H$2:$H$219,"No aplica") | F13: =COUNTIFS(Pruebas!$B$2:$B$219,A13,Pruebas!$H$2:$H$219,"Pendiente") | G13: =IF(B13=0,"",1-F13/B13)
... A24: 20. Q1–Q4 · ProjectLibre (opcional, sin Excel) | B24: =COUNTIF(Pruebas!$B$2:$B$219,A24) | C24: =COUNTIFS(Pruebas!$B$2:$B$219,A24,Pruebas!$H$2:$H$219,"OK") | D24: =COUNTIFS(Pruebas!$B$2:$B$219,A24,Pruebas!$H$2:$H$219,"Falla") | E24: =COUNTIFS(Pruebas!$B$2:$B$219,A24,Pruebas!$H$2:$H$219,"No aplica") | F24: =COUNTIFS(Pruebas!$B$2:$B$219,A24,Pruebas!$H$2:$H$219,"Pendiente") | G24: =IF(B24=0,"",1-F24/B24)
A25: Total | B25: =SUM(B2:B24) | C25: =SUM(C2:C24) | D25: =SUM(D2:D24) | E25: =SUM(E2:E24) | F25: =SUM(F2:F24) | G25: =IF(B25=0,"",1-F25/B25)
